MANIFEST.in
README.rst
setup.py
django_pin.egg-info/PKG-INFO
django_pin.egg-info/SOURCES.html
django_pin.egg-info/SOURCES.txt
django_pin.egg-info/dependency_links.html
django_pin.egg-info/dependency_links.txt
django_pin.egg-info/not-zip-safe
django_pin.egg-info/top_level.html
django_pin.egg-info/top_level.txt
pin/__init__.py
pin/admin.py
pin/api.py
pin/crawler.py
pin/feeds.py
pin/forms.py
pin/models.py
pin/pin_image.py
pin/tests.py
pin/tools.py
pin/urls.py
pin/views.py
pin/media/pin/css/bootstrap.css
pin/media/pin/css/bootstrap.min.css
pin/media/pin/css/important.css
pin/media/pin/css/main.css
pin/media/pin/js/bootstrap.js
pin/media/pin/js/bootstrap.min.js
pin/media/pin/js/fileuploader.js
pin/media/pin/js/jquery-ui.js
pin/media/pin/js/jquery.js
pin/media/pin/js/jquery.masonry.min.js
pin/media/pin/js/jquery.tagcloud.js
pin/media/pin/js/rss.js
pin/media/pin/js/textextc.js
pin/migrations/0001_initial.py
pin/migrations/0002_auto__add_category__add_field_post_category.py
pin/migrations/0003_auto__chg_field_post_category.py
pin/migrations/0004_auto__del_category__del_field_post_category.py
pin/migrations/__init__.py
pin/templates/base/all_footer.html
pin/templates/base/all_header.html
pin/templates/base/analytics.html
pin/templates/base/bar_first.html
pin/templates/base/pin.html
pin/templates/pin/_edit.html
pin/templates/pin/_items.html
pin/templates/pin/_send.html
pin/templates/pin/_sendurl.html
pin/templates/pin/delneveshte.html
pin/templates/pin/delneveshte2.html
pin/templates/pin/edit.html
pin/templates/pin/feed_scripts.html
pin/templates/pin/feed_scripts_v2.html
pin/templates/pin/following_box.html
pin/templates/pin/home.html
pin/templates/pin/home_back.html
pin/templates/pin/item.html
pin/templates/pin/item_inner.html
pin/templates/pin/notify.html
pin/templates/pin/pin_scripts.html
pin/templates/pin/send.html
pin/templates/pin/sendurl.html
pin/templates/pin/tag.html
pin/templates/pin/user.html
pin/templates/pin/user_profile.html
pin/templatetags/__init__.py
pin/templatetags/__init__.pyc
pin/templatetags/pin_tags.py
pin/templatetags/pin_tags.pyc