Metadata-Version: 1.1
Name: django-pin
Version: 1.4.5
Summary: pinterest apllication like in Django
Home-page: https://github.com/karoon/django-pin
Author: vahid chakoshy
Author-email: vchakoshy@gmail.com
License: UNKNOWN
Platform: UNKNOWN
Classifier: Framework :: Django
Classifier: Intended Audience :: Developers
Classifier: License :: OSI Approved :: BSD License
Classifier: Operating System :: OS Independent
Classifier: Programming Language :: Python
Classifier: Topic :: Internet :: WWW/HTTP
Classifier: Natural Language :: Persian
